stop_thread/__init__.py
stop_thread/__main__.py-
stop_thread/stop_thread.py
stop_thread-0.1.0.dist-info/entry_points.txt
stop_thread-0.1.0.dist-info/LICENSE
stop_thread-0.1.0.dist-info/WHEEL
stop_thread-0.1.0.dist-info/METADATA
stop_thread-0.1.0.dist-info/RECORD
