Metadata-Version: 2.1
Name: stop-thread
Version: 0.1.0
Summary: Stop a thread in a nasty way
Home-page: https://github.com/ffreemt/stop-thread
License: MIT
Author: ffreemt
Requires-Python: >=3.8.3,<4.0.0
Classifier: License :: OSI Approved :: MIT License
Classifier: Programming Language :: Python :: 3
Classifier: Programming Language :: Python :: 3.10
Classifier: Programming Language :: Python :: 3.9
Requires-Dist: logzero (>=1.7.0,<2.0.0)
Project-URL: Repository, https://github.com/ffreemt/stop-thread
